{
  "project_info": {
    "project_number": "236206598377",
    "project_id": "mob-universal",
    "storage_bucket": "mob-universal.firebasestorage.app"
  },
  "client": [
    {
      "client_info": {
        "mobilesdk_app_id": "1:236206598377:android:8e7bf1731d82d26bd72878",
        "android_client_info": {
          "package_name": "com.mob.app"
        }
      },
      "oauth_client": [],
      "api_key": [
        {
          "current_key": "AIzaSyD80lNA-9R-VDc21sruOUyJyN3gJ61Xn0I"
        }
      ],
      "services": {
        "appinvite_service": {
          "other_platform_oauth_client": []
        }
      }
    }
  ],
  "configuration_version": "1"
}